LICENSE
README.md
setup.cfg
setup.py
configs/__init__.py
configs/_base_/__init__.py
tools/__init__.py
trademas.egg-info/PKG-INFO
trademas.egg-info/SOURCES.txt
trademas.egg-info/dependency_links.txt
trademas.egg-info/requires.txt
trademas.egg-info/top_level.txt
trademaster/__init__.py
trademaster/agents/__init__.py
trademaster/agents/builder.py
trademaster/agents/custom.py
trademaster/agents/algorithmic_trading/__init__.py
trademaster/agents/algorithmic_trading/dqn.py
trademaster/agents/high_frequency_trading/__init__.py
trademaster/agents/high_frequency_trading/ddqn.py
trademaster/agents/order_execution/__init__.py
trademaster/agents/order_execution/eteo.py
trademaster/agents/order_execution/pd.py
trademaster/agents/portfolio_management/__init__.py
trademaster/agents/portfolio_management/deeptrader.py
trademaster/agents/portfolio_management/eiie.py
trademaster/agents/portfolio_management/investor_imitator.py
trademaster/collector/__init__.py
trademaster/collector/binance.py
trademaster/collector/builder.py
trademaster/collector/custom.py
trademaster/collector/helper/__init__.py
trademaster/collector/helper/celery_app.py
trademaster/collector/helper/celery_config.py
trademaster/collector/helper/pika_connection.py
trademaster/collector/helper/run_celery.py
trademaster/collector/helper/websocket_consumer.py
trademaster/collector/helper/websocket_producer.py
trademaster/datasets/__init__.py
trademaster/datasets/builder.py
trademaster/datasets/custom.py
trademaster/datasets/algorithmic_trading/__init__.py
trademaster/datasets/algorithmic_trading/dataset.py
trademaster/datasets/high_frequency_trading/__init__.py
trademaster/datasets/high_frequency_trading/dataset.py
trademaster/datasets/order_execution/__init__.py
trademaster/datasets/order_execution/dataset.py
trademaster/datasets/portfolio_management/__init__.py
trademaster/datasets/portfolio_management/dataset.py
trademaster/environments/__init__.py
trademaster/environments/builder.py
trademaster/environments/custom.py
trademaster/environments/algorithmic_trading/__init__.py
trademaster/environments/algorithmic_trading/environment.py
