Metadata-Version: 2.1
Name: trademas
Version: 0.0.2
Summary: TradeMaster - A platform for algorithmic trading
Home-page: https://github.com/TradeMaster-NTU/TradeMaster
Author: NTU_trademaster
Author-email: TradeMaster.NTU@gmail.com
License: MIT
Classifier: Programming Language :: Python :: 3
Classifier: License :: OSI Approved :: MIT License
Classifier: Operating System :: OS Independent
Provides-Extra: test
License-File: LICENSE
